fdrtd/plugins/simon/__init__.py
fdrtd/plugins/simon/microservice.py
fdrtd/plugins/simon/peer_to_peer.py
fdrtd/plugins/simon/sync_api.py
fdrtd/plugins/simon/task.py
fdrtd/plugins/simon/accumulators/accumulator.py
fdrtd/plugins/simon/accumulators/accumulator_basic_function.py
fdrtd/plugins/simon/accumulators/accumulator_basic_minimum_maximum.py
fdrtd/plugins/simon/accumulators/accumulator_basic_sum.py
fdrtd/plugins/simon/accumulators/accumulator_generic.py
fdrtd/plugins/simon/accumulators/accumulator_generic_dictionary.py
fdrtd/plugins/simon/accumulators/accumulator_set_intersection.py
fdrtd/plugins/simon/accumulators/accumulator_set_intersection_size.py
fdrtd/plugins/simon/accumulators/accumulator_set_union.py
fdrtd/plugins/simon/accumulators/accumulator_statistics_bivariate.py
fdrtd/plugins/simon/accumulators/accumulator_statistics_contingency.py
fdrtd/plugins/simon/accumulators/accumulator_statistics_frequency.py
fdrtd/plugins/simon/accumulators/accumulator_statistics_moments.py
fdrtd/plugins/simon/accumulators/accumulator_statistics_univariate.py
fdrtd/plugins/simon/accumulators/create.py
fdrtd/plugins/simon/caches/additive.py
fdrtd/plugins/simon/caches/cache.py
fdrtd/plugins/simon/caches/functional.py
fdrtd/plugins/simon/caches/multiplicative.py
fdrtd/plugins/simon/crypto/x25519x448.py
fdrtd/plugins/simon/microprotocols/create.py
fdrtd/plugins/simon/microprotocols/microprotocol.py
fdrtd/plugins/simon/microprotocols/microprotocol_minimum_maximum.py
fdrtd/plugins/simon/microprotocols/microprotocol_secure_matrix_multiplication.py
fdrtd/plugins/simon/microprotocols/microprotocol_secure_sum.py
fdrtd/plugins/simon/microprotocols/microprotocol_set_intersection.py
fdrtd/plugins/simon/microprotocols/microprotocol_set_intersection_size.py
fdrtd/plugins/simon/microprotocols/microprotocol_statistics_bivariate.py
fdrtd/plugins/simon/microprotocols/microprotocol_statistics_contingency.py
fdrtd/plugins/simon/microprotocols/microprotocol_statistics_contingency_vertical.py
fdrtd_simon-0.5.7.dist-info/METADATA
fdrtd_simon-0.5.7.dist-info/WHEEL
fdrtd_simon-0.5.7.dist-info/top_level.txt
fdrtd_simon-0.5.7.dist-info/RECORD
